hkube_debbuging_python_api/__init__.py
hkube_debbuging_python_api/__version__.py
hkube_debbuging_python_api/algorithm.py
hkube_debbuging_python_api/builder.py
hkube_debbuging_python_api/communication.py
hkube_debbuging_python_api/consts.py
hkube_debbuging_python_api/flow_input.py
hkube_debbuging_python_api/hkube_api_mock.py
hkube_debbuging_python_api/pipeline.py
hkube_debbuging_python_api/wcClient.py
hkube.debbuging_python_api-0.0.5.dist-info/METADATA
hkube.debbuging_python_api-0.0.5.dist-info/WHEEL
hkube.debbuging_python_api-0.0.5.dist-info/top_level.txt
hkube.debbuging_python_api-0.0.5.dist-info/RECORD
