Metadata-Version: 2.1
Name: hkube.debbuging-python-api
Version: 0.0.5
Summary: Hkube Python Api
Home-page: https://github.com/kube-HPC/hkube.debbuging-python-api
Author: Maty Zisserman
Author-email: hkube.dev@gmail.com
License: MIT
Platform: UNKNOWN
Classifier: Programming Language :: Python :: 3
Classifier: License :: OSI Approved :: MIT License
Classifier: Operating System :: OS Independent
Requires-Dist: Events (>=0.3)
Requires-Dist: websocket-client (==0.53.0)
Requires-Dist: simplejson
